protein_design_tools/__init__.py
protein_design_tools/alignment/__init__.py
protein_design_tools/alignment/superpose.py
protein_design_tools/core/__init__.py
protein_design_tools/core/atom.py
protein_design_tools/core/chain.py
protein_design_tools/core/protein_structure.py
protein_design_tools/core/residue.py
protein_design_tools/io/__init__.py
protein_design_tools/io/cif.py
protein_design_tools/io/pdb.py
protein_design_tools/io/write.py
protein_design_tools/metrics/__init__.py
protein_design_tools/metrics/gdt.py
protein_design_tools/metrics/lddt.py
protein_design_tools/metrics/rmsd.py
protein_design_tools/metrics/tmscore.py
protein_design_tools/utils/__init__.py
protein_design_tools/utils/analysis.py
protein_design_tools/utils/helpers.py
protein_design_tools-0.1.31.dist-info/licenses/LICENSE
protein_design_tools-0.1.31.dist-info/METADATA
protein_design_tools-0.1.31.dist-info/WHEEL
protein_design_tools-0.1.31.dist-info/top_level.txt
protein_design_tools-0.1.31.dist-info/RECORD
