Metadata-Version: 2.4
Name: protein-design-tools
Version: 0.1.31
Summary: A toolkit for protein structure analysis and design.
Home-page: https://github.com/drewschaub/protein-design-tools
Author: Andrew Schaub
Author-email: andrew.schaub@protonmail.com
License:  MIT License
Classifier: Development Status :: 2 - Pre-Alpha
Classifier: Intended Audience :: Developers
Classifier: Intended Audience :: Science/Research
Classifier: License :: OSI Approved :: MIT License
Classifier: Operating System :: OS Independent
Classifier: Programming Language :: Python :: 3
Requires-Python: >=3.6
License-File: LICENSE
Requires-Dist: freesasa
Requires-Dist: h5py
Requires-Dist: numpy==1.26.4
Requires-Dist: requests
Requires-Dist: torch
Requires-Dist: sphinx_rtd_theme
Provides-Extra: jax-cpu
Requires-Dist: jax[cpu]==0.4.25; extra == "jax-cpu"
Provides-Extra: jax-cuda12
Requires-Dist: jax[cuda12]; extra == "jax-cuda12"
Provides-Extra: jax-tpu
Requires-Dist: jax[tpu]; extra == "jax-tpu"
Dynamic: author
Dynamic: author-email
Dynamic: classifier
Dynamic: description
Dynamic: description-content-type
Dynamic: home-page
Dynamic: license
Dynamic: license-file
Dynamic: provides-extra
Dynamic: requires-dist
Dynamic: requires-python
Dynamic: summary
